src/counter_design.v
module d_flipflop(
    input clk,
    input reset,
    input D,
    output reg Q
);

always @(posedge clk or posedge reset)
begin
    if (reset)
        Q <= 0;
    else
        Q <= D;
end

endmodule


module synchronous_counter(
    input clk,
    input reset,
    output [3:0] Q
);

wire q0, q1, q2, q3;

d_flipflop FF0(clk, reset, ~q0, q0);
d_flipflop FF1(clk, reset, q1 ^ q0, q1);
d_flipflop FF2(clk, reset, q2 ^ (q0 & q1), q2);
d_flipflop FF3(clk, reset, q3 ^ (q0 & q1 & q2), q3);

assign Q = {q3, q2, q1, q0};

endmodule

testbench/counter_design_tb.v
`timescale 1ns/1ps

module counter_design_tb;

reg clk;
reg reset;

wire [3:0] Q;

synchronous_counter uut (
    .clk(clk),
    .reset(reset),
    .Q(Q)
);

initial begin
    clk = 0;
    forever #5 clk = ~clk;
end

initial begin

    $dumpfile("counter_design.vcd");
    $dumpvars(0, counter_design_tb);

    reset = 1;
    #10;

    reset = 0;

    #100;

    $finish;
end

endmodule

testbench/counter_design.vcd
$date
	Fri May 29 05:51:16 2026
$end
$version
	Icarus Verilog
$end
$timescale
	1ps
$end
$scope module counter_design_tb $end
$var wire 4 ! Q [3:0] $end
$var reg 1 " clk $end
$var reg 1 # reset $end
$scope module uut $end
$var wire 1 " clk $end
$var wire 1 # reset $end
$var wire 1 $ q3 $end
$var wire 1 % q2 $end
$var wire 1 & q1 $end
$var wire 1 ' q0 $end
$var wire 4 ( Q [3:0] $end
$scope module FF0 $end
$var wire 1 ) D $end
$var wire 1 " clk $end
$var wire 1 # reset $end
$var reg 1 ' Q $end
$upscope $end
$scope module FF1 $end
$var wire 1 * D $end
$var wire 1 " clk $end
$var wire 1 # reset $end
$var reg 1 & Q $end
$upscope $end
$scope module FF2 $end
$var wire 1 + D $end
$var wire 1 " clk $end
$var wire 1 # reset $end
$var reg 1 % Q $end
$upscope $end
$scope module FF3 $end
$var wire 1 , D $end
$var wire 1 " clk $end
$var wire 1 # reset $end
$var reg 1 $ Q $end
$upscope $end
$upscope $end
$upscope $end
$enddefinitions $end
$comment Show the parameter values. $end
$dumpall
$end
#0
$dumpvars
0,
0+
0*
1)
b0 (
0'
0&
0%
0$
1#
0"
b0 !
$end
#5000
1"
#10000
0"
0#
#15000
1*
0)
b1 !
b1 (
1'
1"
#20000
0"
#25000
1)
1&
b10 !
b10 (
0'
1"
#30000
0"
#35000
1+
0*
0)
b11 !
b11 (
1'
1"
#40000
0"
#45000
1)
1%
0&
b100 !
b100 (
0'
1"
#50000
0"
#55000
1*
0)
b101 !
b101 (
1'
1"
#60000
0"
#65000
1)
1&
b110 !
b110 (
0'
1"
#70000
0"
#75000
1,
0+
0*
0)
b111 !
b111 (
1'
1"
#80000
0"
#85000
1)
1$
0%
0&
b1000 !
b1000 (
0'
1"
#90000
0"
#95000
1*
0)
b1001 !
b1001 (
1'
1"
#100000
0"
#105000
1)
1&
b1010 !
b1010 (
0'
1"
